civitai/__init__.py
civitai/api_config.py
civitai/models/AIR.py
civitai/models/ApplyConfigurationJob.py
civitai/models/Assembly.py
civitai/models/AssetType.py
civitai/models/BaseDiffusionModel.py
civitai/models/BaseModel.py
civitai/models/CallingConventions.py
civitai/models/ClearAssetRequest.py
civitai/models/ComfyJob.py
civitai/models/ComfyJobRequest.py
civitai/models/ConstructorInfo.py
civitai/models/ConsumptionDetails.py
civitai/models/CopyAssetRequest.py
civitai/models/CustomAttributeData.py
civitai/models/CustomAttributeNamedArgument.py
civitai/models/CustomAttributeTypedArgument.py
civitai/models/CustomException.py
civitai/models/DeleteBlobRequest.py
civitai/models/EventAttributes.py
civitai/models/EventInfo.py
civitai/models/FieldAttributes.py
civitai/models/FieldInfo.py
civitai/models/GenericParameterAttributes.py
civitai/models/GetBlobRequest.py
civitai/models/ICustomAttributeProvider.py
civitai/models/ImageEmbeddingJob.py
civitai/models/ImageEmbeddingJobRequest.py
civitai/models/ImageJobControlNet.py
civitai/models/ImageJobNetworkParams.py
civitai/models/ImageJobParams.py
civitai/models/ImageResourceTrainingJob.py
civitai/models/ImageResourceTrainingJobRequest.py
civitai/models/ImageTransformJob.py
civitai/models/ImageTransformJobRequest.py
civitai/models/ImageTransformer.py
civitai/models/IntPtr.py
civitai/models/Job.py
civitai/models/JobDetails.py
civitai/models/JobEvent.py
civitai/models/JobEventType.py
civitai/models/JobRequest.py
civitai/models/JobStatus.py
civitai/models/JobStatusCollection.py
civitai/models/JobSupport.py
civitai/models/JobTemplateList.py
civitai/models/LayoutKind.py
civitai/models/MediaTaggingJob.py
civitai/models/MediaTaggingJobRequest.py
civitai/models/MemberInfo.py
civitai/models/MemberTypes.py
civitai/models/MethodAttributes.py
civitai/models/MethodBase.py
civitai/models/MethodImplAttributes.py
civitai/models/MethodInfo.py
civitai/models/ModelError.py
civitai/models/ModelStateEntry.py
civitai/models/ModelValidationState.py
civitai_py-0.1.9.dist-info/METADATA
civitai_py-0.1.9.dist-info/WHEEL
civitai_py-0.1.9.dist-info/RECORD
