Metadata-Version: 2.1
Name: civitai-py
Version: 0.1.9
Summary: Civitai Python SDK
Home-page: https://github.com/civitai/civitai-python
License: MIT
Keywords: Civitai Python SDK,Civitai
Author: Civitai
Author-email: hello@civitai.com
Requires-Python: >=3.7,<4.0
Classifier: License :: OSI Approved :: MIT License
Classifier: Programming Language :: Python :: 3
Classifier: Programming Language :: Python :: 3.7
Classifier: Programming Language :: Python :: 3.8
Classifier: Programming Language :: Python :: 3.9
Classifier: Programming Language :: Python :: 3.10
Classifier: Programming Language :: Python :: 3.11
Classifier: Programming Language :: Python :: 3.12
Requires-Dist: pydantic (>=2)
Requires-Dist: typing-extensions (>=4.7.1)
Requires-Dist: urllib3 (>=1.25.3)
Project-URL: Repository, https://github.com/civitai/civitai-python
